{
  "metadata": {
    "vessel": "Arrowhead",
    "units": {
      "sounding": "feet and inches",
      "volume_primary": "gallons",
      "volume_metric": "cubic_meters"
    },
    "conversion_factor_gal_to_m3": 0.00378541
  },
  "tanks": {
    "17P": {
      "name": "Oily Water Tank",
      "orb_code": "I",
      "capacity_gallons": 1607,
      "capacity_m3": 6.08,
      "soundings": [
        {"feet": 0, "inches": 0, "gallons": 0},
        {"feet": 0, "inches": 1, "gallons": 4},
        {"feet": 0, "inches": 2, "gallons": 17},
        {"feet": 0, "inches": 3, "gallons": 34},
        {"feet": 0, "inches": 4, "gallons": 54},
        {"feet": 0, "inches": 5, "gallons": 77},
        {"feet": 0, "inches": 6, "gallons": 105},
        {"feet": 0, "inches": 7, "gallons": 137},
        {"feet": 0, "inches": 8, "gallons": 173},
        {"feet": 0, "inches": 9, "gallons": 208},
        {"feet": 0, "inches": 10, "gallons": 244},
        {"feet": 0, "inches": 11, "gallons": 282},
        {"feet": 1, "inches": 0, "gallons": 323},
        {"feet": 1, "inches": 1, "gallons": 366},
        {"feet": 1, "inches": 2, "gallons": 413},
        {"feet": 1, "inches": 3, "gallons": 462},
        {"feet": 1, "inches": 4, "gallons": 513},
        {"feet": 1, "inches": 5, "gallons": 565},
        {"feet": 1, "inches": 6, "gallons": 619},
        {"feet": 1, "inches": 7, "gallons": 673},
        {"feet": 1, "inches": 8, "gallons": 728},
        {"feet": 1, "inches": 9, "gallons": 783},
        {"feet": 1, "inches": 10, "gallons": 839},
        {"feet": 1, "inches": 11, "gallons": 894},
        {"feet": 2, "inches": 0, "gallons": 950},
        {"feet": 2, "inches": 1, "gallons": 1005},
        {"feet": 2, "inches": 2, "gallons": 1061},
        {"feet": 2, "inches": 3, "gallons": 1117},
        {"feet": 2, "inches": 4, "gallons": 1172},
        {"feet": 2, "inches": 5, "gallons": 1228},
        {"feet": 2, "inches": 6, "gallons": 1283},
        {"feet": 2, "inches": 7, "gallons": 1339},
        {"feet": 2, "inches": 8, "gallons": 1394},
        {"feet": 2, "inches": 9, "gallons": 1450},
        {"feet": 2, "inches": 10, "gallons": 1505},
        {"feet": 2, "inches": 11, "gallons": 1561},
        {"feet": 3, "inches": 0, "gallons": 1607}
      ]
    },
    "17S": {
      "name": "Dirty Oil Tank",
      "orb_code": "C",
      "capacity_gallons": 1607,
      "capacity_m3": 6.08,
      "soundings": [
        {"feet": 0, "inches": 0, "gallons": 0},
        {"feet": 0, "inches": 1, "gallons": 4},
        {"feet": 0, "inches": 2, "gallons": 17},
        {"feet": 0, "inches": 3, "gallons": 34},
        {"feet": 0, "inches": 4, "gallons": 54},
        {"feet": 0, "inches": 5, "gallons": 77},
        {"feet": 0, "inches": 6, "gallons": 105},
        {"feet": 0, "inches": 7, "gallons": 137},
        {"feet": 0, "inches": 8, "gallons": 173},
        {"feet": 0, "inches": 9, "gallons": 208},
        {"feet": 0, "inches": 10, "gallons": 244},
        {"feet": 0, "inches": 11, "gallons": 282},
        {"feet": 1, "inches": 0, "gallons": 323},
        {"feet": 1, "inches": 1, "gallons": 366},
        {"feet": 1, "inches": 2, "gallons": 413},
        {"feet": 1, "inches": 3, "gallons": 462},
        {"feet": 1, "inches": 4, "gallons": 513},
        {"feet": 1, "inches": 5, "gallons": 565},
        {"feet": 1, "inches": 6, "gallons": 619},
        {"feet": 1, "inches": 7, "gallons": 673},
        {"feet": 1, "inches": 8, "gallons": 728},
        {"feet": 1, "inches": 9, "gallons": 783},
        {"feet": 1, "inches": 10, "gallons": 839},
        {"feet": 1, "inches": 11, "gallons": 894},
        {"feet": 2, "inches": 0, "gallons": 950},
        {"feet": 2, "inches": 1, "gallons": 1005},
        {"feet": 2, "inches": 2, "gallons": 1061},
        {"feet": 2, "inches": 3, "gallons": 1117},
        {"feet": 2, "inches": 4, "gallons": 1172},
        {"feet": 2, "inches": 5, "gallons": 1228},
        {"feet": 2, "inches": 6, "gallons": 1283},
        {"feet": 2, "inches": 7, "gallons": 1339},
        {"feet": 2, "inches": 8, "gallons": 1394},
        {"feet": 2, "inches": 9, "gallons": 1450},
        {"feet": 2, "inches": 10, "gallons": 1505},
        {"feet": 2, "inches": 11, "gallons": 1561},
        {"feet": 3, "inches": 0, "gallons": 1607}
      ]
    }
  }
}
